odoo/addons/helpdesk_mgmt_crm/README.rst
odoo/addons/helpdesk_mgmt_crm/__init__.py
odoo/addons/helpdesk_mgmt_crm/__manifest__.py
odoo/addons/helpdesk_mgmt_crm/i18n/es.po
odoo/addons/helpdesk_mgmt_crm/i18n/helpdesk_mgmt_crm.pot
odoo/addons/helpdesk_mgmt_crm/i18n/it.po
odoo/addons/helpdesk_mgmt_crm/models/__init__.py
odoo/addons/helpdesk_mgmt_crm/models/crm_lead.py
odoo/addons/helpdesk_mgmt_crm/models/helpdesk_ticket.py
odoo/addons/helpdesk_mgmt_crm/readme/CONTRIBUTORS.md
odoo/addons/helpdesk_mgmt_crm/readme/DESCRIPTION.md
odoo/addons/helpdesk_mgmt_crm/readme/USAGE.md
odoo/addons/helpdesk_mgmt_crm/security/ir.model.access.csv
odoo/addons/helpdesk_mgmt_crm/static/description/icon.png
odoo/addons/helpdesk_mgmt_crm/static/description/icon.svg
odoo/addons/helpdesk_mgmt_crm/static/description/index.html
odoo/addons/helpdesk_mgmt_crm/tests/__init__.py
odoo/addons/helpdesk_mgmt_crm/tests/test_helpdesk_mgmt_crm.py
odoo/addons/helpdesk_mgmt_crm/views/crm_lead_view.xml
odoo/addons/helpdesk_mgmt_crm/views/helpdesk_ticket_view.xml
odoo/addons/helpdesk_mgmt_crm/wizard/__init__.py
odoo/addons/helpdesk_mgmt_crm/wizard/helpdesk_ticket_create_lead.py
odoo/addons/helpdesk_mgmt_crm/wizard/helpdesk_ticket_create_lead_views.xml
odoo_addon_helpdesk_mgmt_crm-18.0.1.0.1.dist-info/METADATA
odoo_addon_helpdesk_mgmt_crm-18.0.1.0.1.dist-info/WHEEL
odoo_addon_helpdesk_mgmt_crm-18.0.1.0.1.dist-info/top_level.txt
odoo_addon_helpdesk_mgmt_crm-18.0.1.0.1.dist-info/RECORD
